{"data":{"allResumeProficienciesJson":{"edges":[{"node":{"languages":["JavaScript","Python","SQL","PHP"],"tools":null,"skills":null}},{"node":{"languages":null,"tools":["Docker","Drupal","Git","GraphQL","New Relic","Node.js","PostgreSQL","React","Redis","Varnish/VCL"],"skills":null}},{"node":{"languages":null,"tools":null,"skills":["Agile methodology","Bash scripting","Continuous integration","Data analysis","Data migration","Data visualization","DevOps","Performance auditing","Statistics","Technical documentation","User experience","Wireframing"]}}]}}}